{
  "users": [
    {
      "email": "Johndoe@mailinator.com",
      "password": "$2a$10$UyLQVi8COkbqYKmhNGa9E.z.oF5q2sZYaYrQ3obWqG8TBHRxrEmry",
      "name": "John Doe",
      "id": 1
    },
    {
      "email": "janedoe@mailinator.com",
      "password": "$2a$10$k2sW4.vr9Jre3gTYAHS9KOCqKPD.UewL9/HsdrOBW8zFUtNhRNu/y",
      "name": "Jane Doe",
      "id": 2
    },
    {
      "email": "Jonas.doe@mailinator.com",
      "password": "$2a$10$Z3mXUWtOZeaJZy33yTzJmOTM3t.YXE.jZu2fbxi4fdvsFXPkudcGO",
      "name": "Jonas Doe",
      "id": 3
    }
  ],
  "favmovies": [
    {
      "userId": 3,
      "movieId": 357138,
      "id": 1
    },
    {
      "userId": 3,
      "movieId": 299536,
      "id": 2
    },
    {
      "userId": 3,
      "movieId": 767,
      "id": 3
    }
  ]
}